MANIFEST.in
README.md
setup.py
sfdmap.py
licenses/ASTROPY_LICENSE
licenses/LICENSE
sfdmap.egg-info/PKG-INFO
sfdmap.egg-info/SOURCES.txt
sfdmap.egg-info/dependency_links.txt
sfdmap.egg-info/requires.txt
sfdmap.egg-info/top_level.txt