Metadata-Version: 1.1
Name: sfdmap
Version: 0.1.1
Summary: Get E(B-V) values from Schlegel et al (1998) dust maps
Home-page: http://github.com/kbarbary/sfdmap
Author: Kyle Barbary
Author-email: kylebarbary@gmail.com
License: UNKNOWN
Platform: UNKNOWN
Classifier: Development Status :: 4 - Beta
Classifier: Programming Language :: Python :: 2
Classifier: Programming Language :: Python :: 3
Classifier: License :: OSI Approved :: MIT License
Classifier: Topic :: Scientific/Engineering
Classifier: Topic :: Scientific/Engineering :: Astronomy
Classifier: Intended Audience :: Science/Research
